LICENSE
setup.py
max_bot_api_client.egg-info/PKG-INFO
max_bot_api_client.egg-info/SOURCES.txt
max_bot_api_client.egg-info/dependency_links.txt
max_bot_api_client.egg-info/requires.txt
max_bot_api_client.egg-info/top_level.txt
max_client/__init__.py
max_client/api_client.py
max_client/cmn.py
max_client/configuration.py
max_client/max_chat.py
max_client/max_commander.py
max_client/max_editmessage.py
max_client/max_repiter.py
max_client/rest.py
max_client/utl.py
max_client/api/__init__.py
max_client/api/bots_api.py
max_client/api/chats_api.py
max_client/api/messages_api.py
max_client/api/subscriptions_api.py
max_client/api/upload_api.py
max_client/models/__init__.py
max_client/models/action_request_body.py
max_client/models/attachment.py
max_client/models/attachment_payload.py
max_client/models/attachment_request.py
max_client/models/audio_attachment.py
max_client/models/audio_attachment_request.py
max_client/models/bot_added_to_chat_update.py
max_client/models/bot_command.py
max_client/models/bot_info.py
max_client/models/bot_patch.py
max_client/models/bot_removed_from_chat_update.py
max_client/models/bot_started_update.py
max_client/models/button.py
max_client/models/callback.py
max_client/models/callback_answer.py
max_client/models/callback_button.py
max_client/models/chat.py
max_client/models/chat_admin.py
max_client/models/chat_admin_permission.py
max_client/models/chat_admins_list.py
max_client/models/chat_button.py
max_client/models/chat_list.py
max_client/models/chat_member.py
max_client/models/chat_members_list.py
max_client/models/chat_patch.py
max_client/models/chat_status.py
max_client/models/chat_title_changed_update.py
max_client/models/chat_type.py
max_client/models/contact_attachment.py
max_client/models/contact_attachment_payload.py
max_client/models/contact_attachment_request.py
max_client/models/contact_attachment_request_payload.py
max_client/models/data_attachment.py
max_client/models/emphasized_markup.py
max_client/models/error.py
max_client/models/file_attachment.py
max_client/models/file_attachment_payload.py
max_client/models/file_attachment_request.py
max_client/models/get_pinned_message_result.py
max_client/models/get_subscriptions_result.py
