Metadata-Version: 2.1
Name: max-bot-api-client
Version: 0.2.dev0
Summary: Max Bot API
Home-page: https://github.com/max-messenger/max-bot-api-client-py
Author-email: d.sigaev@juicedev.org
License: GNU LGPL v3.0
Keywords: Max Bot API
Classifier: License :: OSI Approved :: GNU Lesser General Public License v3 (LGPLv3)
Classifier: Programming Language :: Python
License-File: LICENSE
